wolfsoftware/get_language_versions/__init__.py
wolfsoftware/get_language_versions/cli.py
wolfsoftware/get_language_versions/config.py
wolfsoftware/get_language_versions/constants.py
wolfsoftware/get_language_versions/exceptions.py
wolfsoftware/get_language_versions/globals.py
wolfsoftware/get_language_versions/main.py
wolfsoftware/get_language_versions/process.py
wolfsoftware/get_language_versions/tags.py
wolfsoftware/get_language_versions/utils.py
wolfsoftware/get_language_versions/versions.py
wolfsoftware.get_language_versions-0.1.2.dist-info/LICENSE.md
wolfsoftware.get_language_versions-0.1.2.dist-info/METADATA
wolfsoftware.get_language_versions-0.1.2.dist-info/WHEEL
wolfsoftware.get_language_versions-0.1.2.dist-info/entry_points.txt
wolfsoftware.get_language_versions-0.1.2.dist-info/top_level.txt
wolfsoftware.get_language_versions-0.1.2.dist-info/RECORD
