Metadata-Version: 2.1
Name: wolfsoftware.get-language-versions
Version: 0.1.2
Summary: Fetch up-to-date data on the latest version(s) available on Github Actions for a given set of languages.
Home-page: https://github.com/DevelopersToolbox/get-language-verisons
Author: Wolf Software
Author-email: pypi@wolfsoftware.com
Project-URL: Source, https://github.com/DevelopersToolbox/get-language-verisons
Project-URL: Tracker, https://github.com/DevelopersToolbox/get-language-verisons/issues/
Project-URL: Documentation, https://github.com/DevelopersToolbox/get-language-verisons
Project-URL: Funding, https://ko-fi.com/wolfsoftware
Project-URL: Say Thanks!, https://github.com/sponsors/TGWolf
Classifier: Environment :: Console
Classifier: Intended Audience :: Developers
Classifier: Programming Language :: Python :: 3
Classifier: License :: OSI Approved :: MIT License
Classifier: Operating System :: OS Independent
Classifier: Topic :: Software Development
Requires-Python: >=3.9
License-File: LICENSE.md
Requires-Dist: beautifulsoup4 ==4.12.3
Requires-Dist: colorama ==0.4.6
Requires-Dist: requests ==2.32.3
Requires-Dist: yaspin ==3.0.2
Requires-Dist: packaging ==24.1
Requires-Dist: wolfsoftware.notify ==0.1.0
